easy_env/__init__.py
easy_env/getters.py
easy_env/setters.py
easy_env-0.1.3.dist-info/DESCRIPTION.rst
easy_env-0.1.3.dist-info/METADATA
easy_env-0.1.3.dist-info/RECORD
easy_env-0.1.3.dist-info/WHEEL
easy_env-0.1.3.dist-info/metadata.json
easy_env-0.1.3.dist-info/top_level.txt
