Metadata-Version: 2.0
Name: easy-env
Version: 0.1.3
Summary: Better environ getter.
Home-page: https://github.com/vaniakosmos/easy_env
Author: Bachynin Ivan
Author-email: bachynin.i@gmail.com
License: MIT
Keywords: env,environ
Platform: UNKNOWN
Classifier: Development Status :: 4 - Beta
Classifier: Intended Audience :: Developers
Classifier: License :: OSI Approved :: MIT License
Classifier: Programming Language :: Python
Classifier: Programming Language :: Python :: 3.5
Classifier: Programming Language :: Python :: 3.6
Classifier: Topic :: Utilities
